[{"path":["home","alternate_languages"],"type":"AlternateLanguages"},{"path":["home","data"],"type":"PrismicHomeDataType"},{"path":["home","data","display_name"],"type":"PrismicStructuredTextType"},{"path":["home","data","body","intro_section","primary","heading"],"type":"PrismicStructuredTextType"},{"path":["home","data","body","intro_section","primary","text"],"type":"PrismicStructuredTextType"},{"path":["home","data","body","intro_section","primary"],"type":"PrismicHomeBodyIntroSectionPrimaryType"},{"path":["home","data","body","intro_section","items","image"],"type":"PrismicImageType"},{"path":["home","data","body","intro_section","items"],"type":"[PrismicHomeBodyIntroSectionItemType]"},{"path":["home","data","body","intro_section"],"type":"PrismicHomeBodyIntroSection"},{"path":["home","data","body","events_section","primary","heading"],"type":"PrismicStructuredTextType"},{"path":["home","data","body","events_section","primary"],"type":"PrismicHomeBodyEventsSectionPrimaryType"},{"path":["home","data","body","events_section"],"type":"PrismicHomeBodyEventsSection"},{"path":["home","data","body","memberships","primary","heading"],"type":"PrismicStructuredTextType"},{"path":["home","data","body","memberships","primary","text"],"type":"PrismicStructuredTextType"},{"path":["home","data","body","memberships","primary","download_membership_pdf"],"type":"PrismicLinkType"},{"path":["home","data","body","memberships","primary"],"type":"PrismicHomeBodyMembershipsPrimaryType"},{"path":["home","data","body","memberships","items","table_start"],"type":"PrismicStructuredTextType"},{"path":["home","data","body","memberships","items","table_end"],"type":"PrismicStructuredTextType"},{"path":["home","data","body","memberships","items"],"type":"[PrismicHomeBodyMembershipsItemType]"},{"path":["home","data","body","memberships"],"type":"PrismicHomeBodyMemberships"},{"path":["home","data","body","atf","primary","claim"],"type":"PrismicStructuredTextType"},{"path":["home","data","body","atf","primary","image_left"],"type":"PrismicImageType"},{"path":["home","data","body","atf","primary","image_right"],"type":"PrismicImageType"},{"path":["home","data","body","atf","primary"],"type":"PrismicHomeBodyAtfPrimaryType"},{"path":["home","data","body","atf"],"type":"PrismicHomeBodyAtf"},{"path":["home","data","body","video","primary","heading"],"type":"PrismicStructuredTextType"},{"path":["home","data","body","video","primary"],"type":"PrismicHomeBodyVideoPrimaryType"},{"path":["home","data","body","video","items","video_embed"],"type":"PrismicEmbedType"},{"path":["home","data","body","video","items"],"type":"[PrismicHomeBodyVideoItemType]"},{"path":["home","data","body","video"],"type":"PrismicHomeBodyVideo"},{"path":["home","data","body"],"type":"[PrismicHomeBodySlicesType]"},{"path":["home"],"type":"PrismicHome"},{"path":["event","uid"],"type":"String"},{"path":["event","alternate_languages"],"type":"AlternateLanguages"},{"path":["event","data"],"type":"PrismicEventDataType"},{"path":["event","data","image"],"type":"PrismicImageType"},{"path":["event","data","name"],"type":"PrismicStructuredTextType"},{"path":["event","data","date"],"type":"PrismicStructuredTextType"},{"path":["event","data","location"],"type":"PrismicStructuredTextType"},{"path":["event","data","image_right"],"type":"PrismicImageType"},{"path":["event","data","description"],"type":"PrismicStructuredTextType"},{"path":["event","data","body","download","items","filename"],"type":"PrismicStructuredTextType"},{"path":["event","data","body","download","items","file"],"type":"PrismicLinkType"},{"path":["event","data","body","download","items"],"type":"[PrismicEventBodyDownloadItemType]"},{"path":["event","data","body","download"],"type":"PrismicEventBodyDownload"},{"path":["event","data","body"],"type":"[PrismicEventBodySlicesType]"},{"path":["event"],"type":"PrismicEvent"}]